outlines_haystack/__init__.py
outlines_haystack/generators/__init__.py
outlines_haystack/generators/azure_openai.py
outlines_haystack/generators/llama_cpp.py
outlines_haystack/generators/mlxlm.py
outlines_haystack/generators/openai.py
outlines_haystack/generators/openai_utils.py
outlines_haystack/generators/transformers.py
outlines_haystack/generators/utils.py
outlines_haystack-0.2.5.dist-info/WHEEL
outlines_haystack-0.2.5.dist-info/METADATA
outlines_haystack-0.2.5.dist-info/RECORD
