Metadata-Version: 2.3
Name: outlines-haystack
Version: 0.2.5
Summary: Use `outlines` generators with Haystack.
Keywords: nlp,machine-learning,ai,haystack,llm,outlines,structured-generation,generative-ai
Author: Edoardo Abati
Classifier: License :: OSI Approved :: MIT License
Classifier: Development Status :: 4 - Beta
Classifier: Programming Language :: Python
Classifier: Programming Language :: Python :: 3.9
Classifier: Programming Language :: Python :: 3.10
Classifier: Programming Language :: Python :: 3.11
Classifier: Programming Language :: Python :: 3.12
Classifier: Programming Language :: Python :: Implementation :: CPython
Classifier: Programming Language :: Python :: Implementation :: PyPy
Requires-Dist: haystack-ai>=2.5.0
Requires-Dist: outlines>=0.2.0,<1.0.0
Requires-Dist: outlines[llamacpp] ; extra == 'llama-cpp'
Requires-Dist: llama-cpp-python ; extra == 'llama-cpp'
Requires-Dist: outlines[mlxlm] ; sys_platform == 'darwin' and extra == 'mlxlm'
Requires-Dist: outlines[openai] ; extra == 'openai'
Requires-Dist: outlines[transformers] ; extra == 'transformers'
Requires-Python: >=3.10, <3.13
Project-URL: Documentation, https://github.com/EdAbati/outlines-haystack#readme
Project-URL: Issues, https://github.com/EdAbati/outlines-haystack/issues
Project-URL: Source, https://github.com/EdAbati/outlines-haystack
Provides-Extra: llama-cpp
Provides-Extra: mlxlm
Provides-Extra: openai
Provides-Extra: transformers
